miau/__init__.py
miau-1.0.1.dist-info/LICENSE
miau-1.0.1.dist-info/METADATA
miau-1.0.1.dist-info/WHEEL
miau-1.0.1.dist-info/top_level.txt
miau-1.0.1.dist-info/RECORD
